dur_utils/__init__.py
dur_utils/colours.py
dur_utils-0.1.dist-info/METADATA
dur_utils-0.1.dist-info/WHEEL
dur_utils-0.1.dist-info/top_level.txt
dur_utils-0.1.dist-info/RECORD
